aes/__init__.py
aes/core.py
ibe/__init__.py
ibe/ibe_rsa.py
res_access_crypto-1.0.0.dist-info/METADATA
res_access_crypto-1.0.0.dist-info/WHEEL
res_access_crypto-1.0.0.dist-info/top_level.txt
res_access_crypto-1.0.0.dist-info/RECORD
