Metadata-Version: 2.1
Name: res-access-crypto
Version: 1.0.0
Summary: A python module with encryption and decryption				algorithms for RSA based IBE and AES
Home-page: UNKNOWN
Author: Eddy Mwenda Mwiti
Author-email: UNKNOWN
License: UNKNOWN
Platform: UNKNOWN
Requires-Dist: asn1crypto (==0.24.0)
Requires-Dist: backcall (==0.1.0)
Requires-Dist: cffi (==1.12.3)
Requires-Dist: cryptography (==2.7)
Requires-Dist: decorator (==4.4.0)
Requires-Dist: ipython (==7.6.1)
Requires-Dist: ipython-genutils (==0.2.0)
Requires-Dist: jedi (==0.14.1)
Requires-Dist: parso (==0.5.1)
Requires-Dist: pexpect (==4.7.0)
Requires-Dist: pickleshare (==0.7.5)
Requires-Dist: prompt-toolkit (==2.0.9)
Requires-Dist: ptyprocess (==0.6.0)
Requires-Dist: pyAesCrypt (==0.4.3)
Requires-Dist: pycparser (==2.19)
Requires-Dist: Pygments (==2.4.2)
Requires-Dist: six (==1.12.0)
Requires-Dist: traitlets (==4.3.2)
Requires-Dist: wcwidth (==0.1.7)
